mypackage/__init__.py
mypackage/test.py
seventhwonder-0.0.1.dist-info/LICENSE.txt
seventhwonder-0.0.1.dist-info/METADATA
seventhwonder-0.0.1.dist-info/WHEEL
seventhwonder-0.0.1.dist-info/top_level.txt
seventhwonder-0.0.1.dist-info/RECORD
