Metadata-Version: 2.1
Name: seventhwonder
Version: 0.0.1
Summary: Simple test package
Author: srikanth
Author-email: kunku.srikanth1234@gmail.com
License-File: LICENSE.txt
